<?xml version="1.0" encoding="GB2312" standalone="no"?>
<form formTitleShowFlag="false" id="RefundRegisterbase_Confirm" title="退费确认表单">
<formelement datatype="0" fieldalign="1" fieldcol="2" fieldname="id" fieldtype="99" formactiveid="1" labelalign="3" labelcol="1" labelname="保后跟踪ID" maxlength="30" mustinput="0" row="1"/>
<formelement datatype="0" fieldalign="1" fieldcol="4" fieldname="pactNo" fieldtype="1" formactiveid="3" labelalign="3" labelcol="3" labelname="委托保证合同编号" maxlength="200" mustinput="0" readonly="1" row="1"/>
<formelement datatype="0" fieldalign="1" fieldcol="2" fieldname="payTaxesNo" fieldtype="1" formactiveid="5" labelalign="3" labelcol="1" labelname="纳税人识别号" mustinput="0" readonly="1" row="1"/>
<formelement datatype="12" fieldalign="1" fieldcol="2" fieldname="pactAmt" fieldtype="1" formactiveid="6" labelalign="3" labelcol="1" labelname="保函金额" mustinput="0" readonly="1" row="2" unit="元"/>
<formelement datatype="12" fieldalign="1" fieldcol="2" fieldname="guaranteeAmt" fieldtype="1" formactiveid="7" labelalign="3" labelcol="1" labelname="应收担保费" maxlength="14" mustinput="0" readonly="1" row="19" unit="元"/>
<formelement datatype="12" fieldalign="1" fieldcol="4" fieldname="handAmt" fieldtype="1" formactiveid="8" labelalign="3" labelcol="3" labelname="应收手续费" maxlength="14" mustinput="0" readonly="1" row="19" unit="元"/>
<formelement datatype="0" fieldalign="1" fieldcol="2" fieldname="cusNo" fieldtype="99" formactiveid="10" labelalign="3" labelcol="1" labelname="申请人编号" maxlength="30" mustinput="0" row="30"/>
<formelement datatype="0" fieldalign="1" fieldcol="6" fieldname="cusName" fieldtype="99" formactiveid="11" labelalign="3" labelcol="5" labelname="客户名称" maxlength="50" mustinput="0" readonly="1" row="1"/>
<formelement datatype="12" fieldalign="1" fieldcol="2" fieldname="actualReceivedBond" fieldtype="1" formactiveid="58" labelalign="3" labelcol="1" labelname="实收保证金" mustinput="0" readonly="1" row="11" unit="元"/>
<formelement datatype="0" fieldalign="1" fieldcol="2" fieldname="lstModTime" fieldtype="99" formactiveid="65" labelalign="3" labelcol="1" labelname="更新时间" maxlength="17" mustinput="0" row="75"/>
<formelement datatype="0" fieldalign="1" fieldcol="2" fieldname="regTime" fieldtype="99" formactiveid="66" labelalign="3" labelcol="1" labelname="创建时间" maxlength="17" mustinput="0" row="75"/>
<formelement datatype="0" fieldalign="1" fieldcol="2" fieldname="fincId" fieldtype="99" formactiveid="78" labelalign="3" labelcol="1" maxlength="30" mustinput="0" row="75"/>
<formelement datatype="0" fieldalign="1" fieldcol="2" fieldname="pactId" fieldtype="99" formactiveid="79" labelalign="3" labelcol="1" maxlength="30" mustinput="0" row="75"/>
<formelement datatype="0" fieldalign="1" fieldcol="2" fieldname="appId" fieldtype="99" formactiveid="81" labelalign="3" labelcol="1" maxlength="30" mustinput="0" row="75"/>
<formelement datatype="0" fieldalign="1" fieldcol="2" fieldname="appName" fieldtype="99" formactiveid="82" labelalign="3" labelcol="1" labelname="项目名称" maxlength="100" mustinput="0" row="75"/>
<formelement datatype="0" fieldalign="1" fieldcol="2" fieldname="kindNo" fieldtype="99" formactiveid="83" labelalign="3" labelcol="1" maxlength="4" mustinput="0" row="75"/>
<formelement datatype="12" fieldalign="1" fieldcol="2" fieldname="bond" fieldtype="1" formactiveid="90" horVer="0" labelalign="3" labelcol="1" labelname="应收保证金" maxlength="14" mustinput="" readonly="1" row="20" unit="元"/>
<formelement datatype="12" fieldalign="1" fieldcol="4" fieldname="actualReceivedHandAmt" fieldtype="1" formactiveid="91" horVer="0" labelalign="3" labelcol="3" labelname="实收手续费" mustinput="" readonly="1" row="10" unit="元"/>
<formelement datatype="0" fieldalign="1" fieldcol="2" fieldcolspan="3" fieldname="confirmRemark" fieldtype="5" formactiveid="94" horVer="0" labelalign="3" labelcol="1" labelname="备注" maxlength="500" mustinput="" readonly="" row="27"/>
<formelement datatype="0" fieldalign="1" fieldcol="6" fieldname="collectAccId" fieldtype="99" formactiveid="96" horVer="0" labelalign="3" labelcol="5" labelname="到账账户关联id" mustinput="" readonly="" row="22"/>
<formelement datatype="12" fieldalign="1" fieldcol="2" fieldname="actualReceivedGuaranteeAmt" fieldtype="1" formactiveid="99" horVer="0" labelalign="3" labelcol="1" labelname="实收担保费" mustinput="" readonly="1" row="10" unit="元"/>
<formelement datatype="12" fieldalign="1" fieldcol="2" fieldname="refundGuaranteeAmt" fieldtype="1" formactiveid="100" horVer="0" labelalign="3" labelcol="1" labelname="应退担保费" maxlength="14" mustinput="0" onchange="MfRefundManage_Insert.refundGuaranteeAmtChange()" readonly="1" row="21" unit="元"/>
<formelement datatype="12" fieldalign="1" fieldcol="4" fieldname="refundHandAmt" fieldtype="1" formactiveid="101" horVer="0" labelalign="3" labelcol="3" labelname="应退手续费" maxlength="14" mustinput="0" onchange="MfRefundManage_Insert.refundHandAmtChange()" readonly="1" row="21" unit="元"/>
<formelement datatype="12" fieldalign="1" fieldcol="2" fieldname="refundBond" fieldtype="1" formactiveid="102" horVer="0" labelalign="3" labelcol="1" labelname="应退保证金" maxlength="14" mustinput="0" onchange="MfRefundManage_Insert.refundBondChange()" readonly="1" row="22" unit="元"/>
<formelement datatype="3" fieldalign="1" fieldcol="2" fieldname="guaranteeRate" fieldtype="1" formactiveid="103" horVer="0" labelalign="3" labelcol="1" labelname="担保费率" mustinput="" readonly="1" row="9" unit="%"/>
<formelement datatype="3" fieldalign="1" fieldcol="4" fieldname="handRate" fieldtype="1" formactiveid="104" horVer="0" labelalign="3" labelcol="3" labelname="手续费率" mustinput="" readonly="1" row="9" unit="%"/>
<formelement datatype="0" fieldalign="1" fieldcol="2" fieldname="anchor1" fieldtype="1" formactiveid="105" horVer="0" labelalign="3" labelcol="1" labelname="锚点开始1" labelstyle="anchor-start" mustinput="" param="[{termType:'1'}]" readonly="" row="3" selrange="1"/>
<formelement datatype="0" fieldalign="1" fieldcol="2" fieldname="anchor1" fieldtype="2" formactiveid="106" horVer="0" labelalign="3" labelcol="1" labelname="锚点结束1" labelstyle="anchor-end" mustinput="" readonly="" row="5" selrange="1"/>
<formelement datatype="0" fieldalign="1" fieldcol="2" fieldname="anchor2" fieldtype="1" formactiveid="107" horVer="0" labelalign="3" labelcol="1" labelname="锚点开始2" labelstyle="anchor-start" mustinput="" param="[{termType:'3'}]" readonly="" row="6" selrange="1"/>
<formelement datatype="0" fieldalign="1" fieldcol="2" fieldname="anchor2" fieldtype="2" formactiveid="108" horVer="0" labelalign="3" labelcol="1" labelname="锚点结束2" labelstyle="anchor-end" mustinput="" readonly="" row="8" selrange="1"/>
<formelement datatype="1" fieldalign="1" fieldcol="2" fieldname="term" fieldtype="1" formactiveid="109" horVer="0" labelalign="3" labelcol="1" labelname="保函期限" mustinput="" readonly="1" row="4" unit="个月"/>
<formelement datatype="6" fieldalign="1" fieldcol="2" fieldname="guaEndDate" fieldtype="1" formactiveid="110" horVer="0" labelalign="3" labelcol="1" labelname="保函到期日" mustinput="" readonly="1" row="7"/>
<formelement datatype="0" fieldalign="1" fieldcol="4" fieldname="termType" fieldsize="TERM_TYPE" fieldstyle="anchor-ctrl" fieldtype="2" formactiveid="111" horVer="0" labelalign="3" labelcol="3" labelname="期限类型" mustinput="" param="anchors:['anchor1','anchor2','anchor3','anchor4']" readonly="1" row="2"/>
<formelement datatype="12" fieldalign="1" fieldcol="2" fieldname="actualPactAmt" fieldtype="1" formactiveid="112" horVer="0" labelalign="3" labelcol="1" labelname="实际保函金额" maxlength="14" mustinput="" readonly="" row="12" unit="元"/>
<formelement datatype="0" fieldalign="1" fieldcol="2" fieldname="anchor3" fieldtype="1" formactiveid="113" horVer="0" labelalign="3" labelcol="1" labelname="锚点开始3" labelstyle="anchor-start" mustinput="" param="[{termType:'1'}]" readonly="" row="13" selrange="1"/>
<formelement datatype="0" fieldalign="1" fieldcol="2" fieldname="anchor3" fieldtype="2" formactiveid="114" horVer="0" labelalign="3" labelcol="1" labelname="锚点结束3" labelstyle="anchor-end" mustinput="" readonly="" row="15" selrange="1"/>
<formelement datatype="0" fieldalign="1" fieldcol="2" fieldname="anchor4" fieldtype="1" formactiveid="115" horVer="0" labelalign="3" labelcol="1" labelname="锚点开始4" labelstyle="anchor-start" mustinput="" param="[{termType:'3'}]" readonly="" row="16" selrange="1"/>
<formelement datatype="0" fieldalign="1" fieldcol="2" fieldname="anchor4" fieldtype="2" formactiveid="116" horVer="0" labelalign="3" labelcol="1" labelname="锚点结束4" labelstyle="anchor-end" mustinput="" readonly="" row="18" selrange="1"/>
<formelement datatype="1" fieldalign="1" fieldcol="2" fieldname="actualTerm" fieldtype="1" formactiveid="117" horVer="0" labelalign="3" labelcol="1" labelname="实际期限" maxlength="10" mustinput="" readonly="1" row="14" unit="个月"/>
<formelement datatype="6" fieldalign="1" fieldcol="2" fieldname="actualGuaEndDate" fieldtype="1" formactiveid="118" horVer="0" labelalign="3" labelcol="1" labelname="实际保函到期日" mustinput="" readonly="1" row="17"/>
<formelement alt="1000字以内" datatype="0" fieldalign="1" fieldcol="2" fieldcolspan="3" fieldname="useOfFunds" fieldtype="5" formactiveid="119" horVer="0" labelalign="3" labelcol="1" labelname="资金用途" maxlength="1000" mustinput="" readonly="1" row="23"/>
<formelement datatype="0" fieldalign="1" fieldcol="2" fieldname="issuingBank" fieldtype="1" formactiveid="120" horVer="0" labelalign="3" labelcol="1" labelname="出票银行" maxlength="200" mustinput="" readonly="1" row="24"/>
<formelement datatype="12" fieldalign="1" fieldcol="2" fieldname="refundAmt" fieldtype="1" formactiveid="121" horVer="0" labelalign="3" labelcol="1" labelname="应退费金额" mustinput="" readonly="1" row="25" unit="元"/>
<formelement datatype="12" fieldalign="1" fieldcol="4" fieldname="actualRefundAmt" fieldtype="1" formactiveid="122" horVer="0" labelalign="3" labelcol="3" labelname="实际退费金额" maxlength="14" mustinput="0" readonly="1" row="25" unit="元"/>
<formelement datatype="12" fieldalign="1" fieldcol="2" fieldname="confirmRefundAmt" fieldtype="1" formactiveid="123" horVer="0" labelalign="3" labelcol="1" labelname="确认退费金额" maxlength="14" mustinput="1" readonly="" row="26" unit="元"/>
</form>
