<?xml version="1.0" encoding="GB2312" standalone="no"?>
<form formTitleShowFlag="false" id="AssetsManageBase" title="资产管理表">
<formelement datatype="0" fieldalign="1" fieldcol="2" fieldname="pledgeNo" fieldtype="1" formactiveid="2" horVer="0" labelalign="3" labelcol="1" labelname="资产名称" maxlength="30" mustinput="1" row="3"/>
<formelement datatype="0" fieldalign="1" fieldcol="2" fieldname="pledgeName" fieldtype="99" formactiveid="3" horVer="0" labelalign="3" labelcol="1" labelname="资产名称" maxlength="100" mustinput="0" row="4"/>
<formelement datatype="0" fieldalign="1" fieldcol="2" fieldname="cusNo" fieldtype="1" formactiveid="4" horVer="0" labelalign="3" labelcol="1" labelname="客户编号" maxlength="30" mustinput="1" readonly="1" row="2"/>
<formelement datatype="0" fieldalign="1" fieldcol="2" fieldname="cusName" fieldtype="1" formactiveid="5" horVer="0" labelalign="3" labelcol="1" labelname="客户名称" maxlength="50" mustinput="1" onclick="selectCusDialog(MfAssetsManage_Insert.callBack,'','','6');" readonly="1" row="1"/>
<formelement datatype="12" fieldalign="1" fieldcol="2" fieldname="assessAmt" fieldtype="1" formactiveid="6" horVer="0" labelalign="3" labelcol="1" labelname="评估价值" maxlength="14" mustinput="0" row="4" unit="元"/>
<formelement datatype="12" fieldalign="1" fieldcol="2" fieldname="debtAmt" fieldtype="1" formactiveid="7" horVer="0" labelalign="3" labelcol="1" labelname="抵债金额" maxlength="14" mustinput="0" row="5" unit="元"/>
<formelement datatype="0" fieldalign="1" fieldcol="2" fieldname="regTime" fieldtype="99" formactiveid="8" horVer="0" labelalign="3" labelcol="1" labelname="创建时间" maxlength="17" mustinput="0" row="12"/>
<formelement datatype="0" fieldalign="1" fieldcol="2" fieldname="opNo" fieldtype="99" formactiveid="9" horVer="0" labelalign="3" labelcol="1" labelname="操作员" maxlength="30" mustinput="0" row="14"/>
<formelement datatype="0" fieldalign="1" fieldcol="2" fieldname="opName" fieldtype="1" formactiveid="10" horVer="0" labelalign="3" labelcol="1" labelname="操作员" maxlength="50" mustinput="0" readonly="1" row="6"/>
<formelement datatype="0" fieldalign="1" fieldcol="2" fieldname="lstModTime" fieldtype="99" formactiveid="11" horVer="1" labelalign="1" labelcol="1" labelname="变更时间" maxlength="17" mustinput="0" row="18"/>
<formelement alt="200字以内" datatype="0" fieldalign="1" fieldcol="2" fieldcolspan="3" fieldname="state" fieldtype="5" formactiveid="12" horVer="0" labelalign="3" labelcol="1" labelname="说明" maxlength="200" mustinput="" readonly="" row="7"/>
</form>
